pyinterconvert/ConvClient.py
pyinterconvert/__init__.py
pyinterconvert-0.1.5.dist-info/LICENSE.txt
pyinterconvert-0.1.5.dist-info/METADATA
pyinterconvert-0.1.5.dist-info/WHEEL
pyinterconvert-0.1.5.dist-info/top_level.txt
pyinterconvert-0.1.5.dist-info/RECORD
